xaal/__init__.py
xaal/conky/__init__.py
xaal/conky/__main__.py
xaal/conky/app.py
xaal_conky-0.1.2.dist-info/METADATA
xaal_conky-0.1.2.dist-info/WHEEL
xaal_conky-0.1.2.dist-info/top_level.txt
xaal_conky-0.1.2.dist-info/RECORD
