Metadata-Version: 2.4
Name: xaal.conky
Version: 0.1.2
Summary: xAAL for Conky
Author-email: Jerome Kerdreux <Jerome.Kerdreux@imt-atlantique.fr>
License-Expression: GPL-3.0-or-later
Keywords: xaal,conky
Classifier: Programming Language :: Python
Classifier: Topic :: Software Development :: Libraries :: Python Modules
Requires-Dist: xaal.lib
Requires-Dist: xaal.monitor
